{
  "generatedAt": "2025-09-07T08:28:22.858Z",
  "year": "2025",
  "count": 58,
  "totalTournaments": 27,
  "players": [
    {
      "name": "Ahmad,Ihtiram",
      "id": "",
      "fideId": "532011059",
      "gender": "male",
      "href": "http://ratings.fide.com/card.phtml?event=532011059",
      "tournamentCount": 4,
      "tournaments": [
        {
          "tournament": "www2025HobsonsBayPurdyCupJuniors/data.json",
          "score": 2,
          "name": "2025 Hobsons Bay Chess Club C.J.S Purdy Cup Juniors",
          "totalRounds": "5",
          "ratingType": "standard"
        },
        {
          "tournament": "www2025HobsonsBayWesternJuniors/data.json",
          "score": 4,
          "name": "2025 Hobsons Bay Western Juniors",
          "totalRounds": "5",
          "ratingType": "standard"
        },
        {
          "tournament": "www2025WesternJuniorRapidChampionship/data.json",
          "score": 3.5,
          "name": "2025 Hobsons Bay Western Juniors Rapid Championship",
          "totalRounds": "7",
          "ratingType": "rapid"
        },
        {
          "tournament": "www2025WesternJuniors/data.json",
          "score": 2,
          "name": "2025 Hobsons Bay Western Juniors",
          "totalRounds": "5",
          "ratingType": "standard"
        }
      ],
      "points": {
        "standard": 8,
        "rapid": 3.5,
        "blitz": 0
      }
    },
    {
      "name": "Annadasu,Shreyansh",
      "id": "",
      "fideId": "3275779",
      "gender": "male",
      "href": "http://ratings.fide.com/card.phtml?event=3275779",
      "tournamentCount": 3,
      "tournaments": [
        {
          "tournament": "www2025HBCCHonourableBobJuniors/data.json",
          "score": 3.5,
          "name": "2025 HBCC Honourable Bob Juniors",
          "totalRounds": "5",
          "ratingType": "standard"
        },
        {
          "tournament": "www2025HobsonsBayPurdyCupJuniors/data.json",
          "score": 3,
          "name": "2025 Hobsons Bay Chess Club C.J.S Purdy Cup Juniors",
          "totalRounds": "5",
          "ratingType": "standard"
        },
        {
          "tournament": "www2025WesternJuniorRapidChampionship/data.json",
          "score": 4,
          "name": "2025 Hobsons Bay Western Juniors Rapid Championship",
          "totalRounds": "7",
          "ratingType": "rapid"
        }
      ],
      "points": {
        "standard": 6.5,
        "rapid": 4,
        "blitz": 0
      }
    },
    {
      "name": "Aryan,Srivatsav Yegnavajjula",
      "id": "",
      "fideId": "",
      "gender": "male",
      "href": "",
      "tournamentCount": 2,
      "tournaments": [
        {
          "tournament": "www2025HobsonsBayWesternMini&RookiesJuniors/data.json",
          "score": 2,
          "name": "2025 Hobsons Bay Western Mini And Rookies Juniors",
          "totalRounds": "5",
          "ratingType": "standard"
        },
        {
          "tournament": "www2025HobsonsBayWesternMiniAndRookiesJuniors/data.json",
          "score": 1.5,
          "name": "2025 Hobsons Bay Western Mini And Rookies Juniors",
          "totalRounds": "5",
          "ratingType": "standard"
        }
      ],
      "points": {
        "standard": 3.5,
        "rapid": 0,
        "blitz": 0
      }
    },
    {
      "name": "Ashok,Arjun",
      "id": "",
      "fideId": "3275108",
      "gender": "male",
      "href": "http://ratings.fide.com/card.phtml?event=3275108",
      "tournamentCount": 5,
      "tournaments": [
        {
          "tournament": "www2025HBCCHonourableBobJuniors/data.json",
          "score": 3,
          "name": "2025 HBCC Honourable Bob Juniors",
          "totalRounds": "5",
          "ratingType": "standard"
        },
        {
          "tournament": "www2025HobsonsBayPurdyCupJuniors/data.json",
          "score": 3,
          "name": "2025 Hobsons Bay Chess Club C.J.S Purdy Cup Juniors",
          "totalRounds": "5",
          "ratingType": "standard"
        },
        {
          "tournament": "www2025HobsonsBayWesternJuniors/data.json",
          "score": 4,
          "name": "2025 Hobsons Bay Western Juniors",
          "totalRounds": "5",
          "ratingType": "standard"
        },
        {
          "tournament": "www2025WesternJuniorRapidChampionship/data.json",
          "score": 4.5,
          "name": "2025 Hobsons Bay Western Juniors Rapid Championship",
          "totalRounds": "7",
          "ratingType": "rapid"
        },
        {
          "tournament": "www2025WesternJuniors/data.json",
          "score": 2,
          "name": "2025 Hobsons Bay Western Juniors",
          "totalRounds": "5",
          "ratingType": "standard"
        }
      ],
      "points": {
        "standard": 12,
        "rapid": 4.5,
        "blitz": 0
      }
    },
    {
      "name": "Balaji,Sai Sivesh",
      "id": "",
      "fideId": "",
      "gender": "male",
      "href": "",
      "tournamentCount": 5,
      "tournaments": [
        {
          "tournament": "www2025HBCCHonourableBobJuniors/data.json",
          "score": 3,
          "name": "2025 HBCC Honourable Bob Juniors",
          "totalRounds": "5",
          "ratingType": "standard"
        },
        {
          "tournament": "www2025HobsonsBayPurdyCupJuniors/data.json",
          "score": 3,
          "name": "2025 Hobsons Bay Chess Club C.J.S Purdy Cup Juniors",
          "totalRounds": "5",
          "ratingType": "standard"
        },
        {
          "tournament": "www2025HobsonsBayWesternJuniors/data.json",
          "score": 4,
          "name": "2025 Hobsons Bay Western Juniors",
          "totalRounds": "5",
          "ratingType": "standard"
        },
        {
          "tournament": "www2025WesternJuniorRapidChampionship/data.json",
          "score": 4.5,
          "name": "2025 Hobsons Bay Western Juniors Rapid Championship",
          "totalRounds": "7",
          "ratingType": "rapid"
        },
        {
          "tournament": "www2025WesternJuniors/data.json",
          "score": 2,
          "name": "2025 Hobsons Bay Western Juniors",
          "totalRounds": "5",
          "ratingType": "standard"
        }
      ],
      "points": {
        "standard": 12,
        "rapid": 4.5,
        "blitz": 0
      }
    },
    {
      "name": "Balamurugan,Soorya",
      "id": "",
      "fideId": "",
      "gender": "male",
      "href": "",
      "tournamentCount": 5,
      "tournaments": [
        {
          "tournament": "www2025HBCCHonourableBobJuniors/data.json",
          "score": 2,
          "name": "2025 HBCC Honourable Bob Juniors",
          "totalRounds": "5",
          "ratingType": "standard"
        },
        {
          "tournament": "www2025HobsonsBayPurdyCupJuniors/data.json",
          "score": 1.5,
          "name": "2025 Hobsons Bay Chess Club C.J.S Purdy Cup Juniors",
          "totalRounds": "5",
          "ratingType": "standard"
        },
        {
          "tournament": "www2025HobsonsBayWesternJuniors/data.json",
          "score": 1,
          "name": "2025 Hobsons Bay Western Juniors",
          "totalRounds": "5",
          "ratingType": "standard"
        },
        {
          "tournament": "www2025WesternJuniorRapidChampionship/data.json",
          "score": 2,
          "name": "2025 Hobsons Bay Western Juniors Rapid Championship",
          "totalRounds": "7",
          "ratingType": "rapid"
        },
        {
          "tournament": "www2025WesternJuniors/data.json",
          "score": 0.5,
          "name": "2025 Hobsons Bay Western Juniors",
          "totalRounds": "5",
          "ratingType": "standard"
        }
      ],
      "points": {
        "standard": 5,
        "rapid": 2,
        "blitz": 0
      }
    },
    {
      "name": "Batyrbekov,Aidan",
      "id": "",
      "fideId": "3265439",
      "gender": "male",
      "href": "http://ratings.fide.com/card.phtml?event=3265439",
      "tournamentCount": 5,
      "tournaments": [
        {
          "tournament": "www2025HBCCHonourableBobJuniors/data.json",
          "score": 3,
          "name": "2025 HBCC Honourable Bob Juniors",
          "totalRounds": "5",
          "ratingType": "standard"
        },
        {
          "tournament": "www2025HobsonsBayPurdyCupJuniors/data.json",
          "score": 3,
          "name": "2025 Hobsons Bay Chess Club C.J.S Purdy Cup Juniors",
          "totalRounds": "5",
          "ratingType": "standard"
        },
        {
          "tournament": "www2025HobsonsBayWesternJuniors/data.json",
          "score": 2.5,
          "name": "2025 Hobsons Bay Western Juniors",
          "totalRounds": "5",
          "ratingType": "standard"
        },
        {
          "tournament": "www2025WesternJuniorRapidChampionship/data.json",
          "score": 4.5,
          "name": "2025 Hobsons Bay Western Juniors Rapid Championship",
          "totalRounds": "7",
          "ratingType": "rapid"
        },
        {
          "tournament": "www2025WesternJuniors/data.json",
          "score": 1.5,
          "name": "2025 Hobsons Bay Western Juniors",
          "totalRounds": "5",
          "ratingType": "standard"
        }
      ],
      "points": {
        "standard": 10,
        "rapid": 4.5,
        "blitz": 0
      }
    },
    {
      "name": "Batyrbekov,Kaisar",
      "id": "",
      "fideId": "3265447",
      "gender": "male",
      "href": "http://ratings.fide.com/card.phtml?event=3265447",
      "tournamentCount": 5,
      "tournaments": [
        {
          "tournament": "www2025HBCCHonourableBobJuniors/data.json",
          "score": 4,
          "name": "2025 HBCC Honourable Bob Juniors",
          "totalRounds": "5",
          "ratingType": "standard"
        },
        {
          "tournament": "www2025HobsonsBayPurdyCupJuniors/data.json",
          "score": 3,
          "name": "2025 Hobsons Bay Chess Club C.J.S Purdy Cup Juniors",
          "totalRounds": "5",
          "ratingType": "standard"
        },
        {
          "tournament": "www2025HobsonsBayWesternJuniors/data.json",
          "score": 3.5,
          "name": "2025 Hobsons Bay Western Juniors",
          "totalRounds": "5",
          "ratingType": "standard"
        },
        {
          "tournament": "www2025WesternJuniorRapidChampionship/data.json",
          "score": 5,
          "name": "2025 Hobsons Bay Western Juniors Rapid Championship",
          "totalRounds": "7",
          "ratingType": "rapid"
        },
        {
          "tournament": "www2025WesternJuniors/data.json",
          "score": 0.5,
          "name": "2025 Hobsons Bay Western Juniors",
          "totalRounds": "5",
          "ratingType": "standard"
        }
      ],
      "points": {
        "standard": 11,
        "rapid": 5,
        "blitz": 0
      }
    },
    {
      "name": "Batyrbekov,Kuanysh",
      "id": "",
      "fideId": "3266150",
      "gender": "male",
      "href": "http://ratings.fide.com/card.phtml?event=3266150",
      "tournamentCount": 4,
      "tournaments": [
        {
          "tournament": "www2025HBCCHonourableBobJuniors/data.json",
          "score": 2,
          "name": "2025 HBCC Honourable Bob Juniors",
          "totalRounds": "5",
          "ratingType": "standard"
        },
        {
          "tournament": "www2025HobsonsBayPurdyCupJuniors/data.json",
          "score": 2.5,
          "name": "2025 Hobsons Bay Chess Club C.J.S Purdy Cup Juniors",
          "totalRounds": "5",
          "ratingType": "standard"
        },
        {
          "tournament": "www2025HobsonsBayWesternJuniors/data.json",
          "score": 3,
          "name": "2025 Hobsons Bay Western Juniors",
          "totalRounds": "5",
          "ratingType": "standard"
        },
        {
          "tournament": "www2025WesternJuniors/data.json",
          "score": 1.5,
          "name": "2025 Hobsons Bay Western Juniors",
          "totalRounds": "5",
          "ratingType": "standard"
        }
      ],
      "points": {
        "standard": 9,
        "rapid": 0,
        "blitz": 0
      }
    },
    {
      "name": "Bodke,Aryan",
      "id": "",
      "fideId": "",
      "gender": "male",
      "href": "",
      "tournamentCount": 5,
      "tournaments": [
        {
          "tournament": "www2025HBCCHonourableBobJuniors/data.json",
          "score": 2,
          "name": "2025 HBCC Honourable Bob Juniors",
          "totalRounds": "5",
          "ratingType": "standard"
        },
        {
          "tournament": "www2025HobsonsBayPurdyCupJuniors/data.json",
          "score": 2,
          "name": "2025 Hobsons Bay Chess Club C.J.S Purdy Cup Juniors",
          "totalRounds": "5",
          "ratingType": "standard"
        },
        {
          "tournament": "www2025HobsonsBayWesternMini&RookiesJuniors/data.json",
          "score": 2.5,
          "name": "2025 Hobsons Bay Western Mini And Rookies Juniors",
          "totalRounds": "5",
          "ratingType": "standard"
        },
        {
          "tournament": "www2025HobsonsBayWesternMiniAndRookiesJuniors/data.json",
          "score": 2,
          "name": "2025 Hobsons Bay Western Mini And Rookies Juniors",
          "totalRounds": "5",
          "ratingType": "standard"
        },
        {
          "tournament": "www2025WesternJuniorRapidChampionship/data.json",
          "score": 3,
          "name": "2025 Hobsons Bay Western Juniors Rapid Championship",
          "totalRounds": "7",
          "ratingType": "rapid"
        }
      ],
      "points": {
        "standard": 8.5,
        "rapid": 3,
        "blitz": 0
      }
    },
    {
      "name": "Bodke,Krishna",
      "id": "",
      "fideId": "3259021",
      "gender": "male",
      "href": "http://ratings.fide.com/card.phtml?event=3259021",
      "tournamentCount": 2,
      "tournaments": [
        {
          "tournament": "www2025HBCCHonourableBobJuniors/data.json",
          "score": 4,
          "name": "2025 HBCC Honourable Bob Juniors",
          "totalRounds": "5",
          "ratingType": "standard"
        },
        {
          "tournament": "www2025WesternJuniorRapidChampionship/data.json",
          "score": 5,
          "name": "2025 Hobsons Bay Western Juniors Rapid Championship",
          "totalRounds": "7",
          "ratingType": "rapid"
        }
      ],
      "points": {
        "standard": 4,
        "rapid": 5,
        "blitz": 0
      }
    },
    {
      "name": "Chan,Abby",
      "id": "",
      "fideId": "",
      "gender": "female",
      "href": "",
      "tournamentCount": 5,
      "tournaments": [
        {
          "tournament": "www2025HBCCHonourableBobJuniors/data.json",
          "score": 1.5,
          "name": "2025 HBCC Honourable Bob Juniors",
          "totalRounds": "5",
          "ratingType": "standard"
        },
        {
          "tournament": "www2025HobsonsBayPurdyCupJuniors/data.json",
          "score": 0.5,
          "name": "2025 Hobsons Bay Chess Club C.J.S Purdy Cup Juniors",
          "totalRounds": "5",
          "ratingType": "standard"
        },
        {
          "tournament": "www2025HobsonsBayWesternMini&RookiesJuniors/data.json",
          "score": 3,
          "name": "2025 Hobsons Bay Western Mini And Rookies Juniors",
          "totalRounds": "5",
          "ratingType": "standard"
        },
        {
          "tournament": "www2025HobsonsBayWesternMiniAndRookiesJuniors/data.json",
          "score": 1,
          "name": "2025 Hobsons Bay Western Mini And Rookies Juniors",
          "totalRounds": "5",
          "ratingType": "standard"
        },
        {
          "tournament": "www2025WesternJuniorRapidChampionship/data.json",
          "score": 2.5,
          "name": "2025 Hobsons Bay Western Juniors Rapid Championship",
          "totalRounds": "7",
          "ratingType": "rapid"
        }
      ],
      "points": {
        "standard": 6,
        "rapid": 2.5,
        "blitz": 0
      }
    },
    {
      "name": "Das,Ayush",
      "id": "",
      "fideId": "",
      "gender": "male",
      "href": "",
      "tournamentCount": 5,
      "tournaments": [
        {
          "tournament": "www2025HBCCHonourableBobJuniors/data.json",
          "score": 1,
          "name": "2025 HBCC Honourable Bob Juniors",
          "totalRounds": "5",
          "ratingType": "standard"
        },
        {
          "tournament": "www2025HobsonsBayPurdyCupJuniors/data.json",
          "score": 1.5,
          "name": "2025 Hobsons Bay Chess Club C.J.S Purdy Cup Juniors",
          "totalRounds": "5",
          "ratingType": "standard"
        },
        {
          "tournament": "www2025HobsonsBayWesternJuniors/data.json",
          "score": 1,
          "name": "2025 Hobsons Bay Western Juniors",
          "totalRounds": "5",
          "ratingType": "standard"
        },
        {
          "tournament": "www2025WesternJuniorRapidChampionship/data.json",
          "score": 3,
          "name": "2025 Hobsons Bay Western Juniors Rapid Championship",
          "totalRounds": "7",
          "ratingType": "rapid"
        },
        {
          "tournament": "www2025WesternJuniors/data.json",
          "score": 0,
          "name": "2025 Hobsons Bay Western Juniors",
          "totalRounds": "5",
          "ratingType": "standard"
        }
      ],
      "points": {
        "standard": 3.5,
        "rapid": 3,
        "blitz": 0
      }
    },
    {
      "name": "Fang,Candice",
      "id": "",
      "fideId": "",
      "gender": "female",
      "href": "",
      "tournamentCount": 3,
      "tournaments": [
        {
          "tournament": "www2025HobsonsBayWesternMini&RookiesJuniors/data.json",
          "score": 2,
          "name": "2025 Hobsons Bay Western Mini And Rookies Juniors",
          "totalRounds": "5",
          "ratingType": "standard"
        },
        {
          "tournament": "www2025HobsonsBayWesternMiniAndRookiesJuniors/data.json",
          "score": 1,
          "name": "2025 Hobsons Bay Western Mini And Rookies Juniors",
          "totalRounds": "5",
          "ratingType": "standard"
        },
        {
          "tournament": "www2025WesternJuniorRapidChampionship/data.json",
          "score": 4,
          "name": "2025 Hobsons Bay Western Juniors Rapid Championship",
          "totalRounds": "7",
          "ratingType": "rapid"
        }
      ],
      "points": {
        "standard": 3,
        "rapid": 4,
        "blitz": 0
      }
    },
    {
      "name": "Goh,Daphne",
      "id": "",
      "fideId": "",
      "gender": "female",
      "href": "",
      "tournamentCount": 5,
      "tournaments": [
        {
          "tournament": "www2025HBCCHonourableBobJuniors/data.json",
          "score": 1,
          "name": "2025 HBCC Honourable Bob Juniors",
          "totalRounds": "5",
          "ratingType": "standard"
        },
        {
          "tournament": "www2025HobsonsBayPurdyCupJuniors/data.json",
          "score": 1.5,
          "name": "2025 Hobsons Bay Chess Club C.J.S Purdy Cup Juniors",
          "totalRounds": "5",
          "ratingType": "standard"
        },
        {
          "tournament": "www2025HobsonsBayWesternMini&RookiesJuniors/data.json",
          "score": 1,
          "name": "2025 Hobsons Bay Western Mini And Rookies Juniors",
          "totalRounds": "5",
          "ratingType": "standard"
        },
        {
          "tournament": "www2025HobsonsBayWesternMiniAndRookiesJuniors/data.json",
          "score": 0,
          "name": "2025 Hobsons Bay Western Mini And Rookies Juniors",
          "totalRounds": "5",
          "ratingType": "standard"
        },
        {
          "tournament": "www2025WesternJuniorRapidChampionship/data.json",
          "score": 2,
          "name": "2025 Hobsons Bay Western Juniors Rapid Championship",
          "totalRounds": "7",
          "ratingType": "rapid"
        }
      ],
      "points": {
        "standard": 3.5,
        "rapid": 2,
        "blitz": 0
      }
    },
    {
      "name": "Goh,Julian",
      "id": "",
      "fideId": "",
      "gender": "male",
      "href": "",
      "tournamentCount": 5,
      "tournaments": [
        {
          "tournament": "www2025HBCCHonourableBobJuniors/data.json",
          "score": 0,
          "name": "2025 HBCC Honourable Bob Juniors",
          "totalRounds": "5",
          "ratingType": "standard"
        },
        {
          "tournament": "www2025HobsonsBayPurdyCupJuniors/data.json",
          "score": 1,
          "name": "2025 Hobsons Bay Chess Club C.J.S Purdy Cup Juniors",
          "totalRounds": "5",
          "ratingType": "standard"
        },
        {
          "tournament": "www2025HobsonsBayWesternMini&RookiesJuniors/data.json",
          "score": 3,
          "name": "2025 Hobsons Bay Western Mini And Rookies Juniors",
          "totalRounds": "5",
          "ratingType": "standard"
        },
        {
          "tournament": "www2025HobsonsBayWesternMiniAndRookiesJuniors/data.json",
          "score": 0,
          "name": "2025 Hobsons Bay Western Mini And Rookies Juniors",
          "totalRounds": "5",
          "ratingType": "standard"
        },
        {
          "tournament": "www2025WesternJuniorRapidChampionship/data.json",
          "score": 3,
          "name": "2025 Hobsons Bay Western Juniors Rapid Championship",
          "totalRounds": "7",
          "ratingType": "rapid"
        }
      ],
      "points": {
        "standard": 4,
        "rapid": 3,
        "blitz": 0
      }
    },
    {
      "name": "Goh,Nicholas",
      "id": "",
      "fideId": "3254917",
      "gender": "male",
      "href": "http://ratings.fide.com/card.phtml?event=3254917",
      "tournamentCount": 5,
      "tournaments": [
        {
          "tournament": "www2025HBCCHonourableBobJuniors/data.json",
          "score": 2,
          "name": "2025 HBCC Honourable Bob Juniors",
          "totalRounds": "5",
          "ratingType": "standard"
        },
        {
          "tournament": "www2025HobsonsBayPurdyCupJuniors/data.json",
          "score": 2,
          "name": "2025 Hobsons Bay Chess Club C.J.S Purdy Cup Juniors",
          "totalRounds": "5",
          "ratingType": "standard"
        },
        {
          "tournament": "www2025HobsonsBayWesternJuniors/data.json",
          "score": 1,
          "name": "2025 Hobsons Bay Western Juniors",
          "totalRounds": "5",
          "ratingType": "standard"
        },
        {
          "tournament": "www2025WesternJuniorRapidChampionship/data.json",
          "score": 4,
          "name": "2025 Hobsons Bay Western Juniors Rapid Championship",
          "totalRounds": "7",
          "ratingType": "rapid"
        },
        {
          "tournament": "www2025WesternJuniors/data.json",
          "score": 0,
          "name": "2025 Hobsons Bay Western Juniors",
          "totalRounds": "5",
          "ratingType": "standard"
        }
      ],
      "points": {
        "standard": 5,
        "rapid": 4,
        "blitz": 0
      }
    },
    {
      "name": "Guggilla,Krithvik",
      "id": "",
      "fideId": "",
      "gender": "male",
      "href": "",
      "tournamentCount": 2,
      "tournaments": [
        {
          "tournament": "www2025HobsonsBayWesternMini&RookiesJuniors/data.json",
          "score": 3,
          "name": "2025 Hobsons Bay Western Mini And Rookies Juniors",
          "totalRounds": "5",
          "ratingType": "standard"
        },
        {
          "tournament": "www2025HobsonsBayWesternMiniAndRookiesJuniors/data.json",
          "score": 2,
          "name": "2025 Hobsons Bay Western Mini And Rookies Juniors",
          "totalRounds": "5",
          "ratingType": "standard"
        }
      ],
      "points": {
        "standard": 5,
        "rapid": 0,
        "blitz": 0
      }
    },
    {
      "name": "Hari,Dhruv",
      "id": "",
      "fideId": "3255360",
      "gender": "male",
      "href": "http://ratings.fide.com/card.phtml?event=3255360",
      "tournamentCount": 2,
      "tournaments": [
        {
          "tournament": "www2025HBCCHonourableBobJuniors/data.json",
          "score": 4.5,
          "name": "2025 HBCC Honourable Bob Juniors",
          "totalRounds": "5",
          "ratingType": "standard"
        },
        {
          "tournament": "www2025WesternJuniorRapidChampionship/data.json",
          "score": 5.5,
          "name": "2025 Hobsons Bay Western Juniors Rapid Championship",
          "totalRounds": "7",
          "ratingType": "rapid"
        }
      ],
      "points": {
        "standard": 4.5,
        "rapid": 5.5,
        "blitz": 0
      }
    },
    {
      "name": "Huang,Michael",
      "id": "",
      "fideId": "",
      "gender": "male",
      "href": "",
      "tournamentCount": 4,
      "tournaments": [
        {
          "tournament": "www2025HBCCHonourableBobJuniors/data.json",
          "score": 3,
          "name": "2025 HBCC Honourable Bob Juniors",
          "totalRounds": "5",
          "ratingType": "standard"
        },
        {
          "tournament": "www2025HobsonsBayPurdyCupJuniors/data.json",
          "score": 3,
          "name": "2025 Hobsons Bay Chess Club C.J.S Purdy Cup Juniors",
          "totalRounds": "5",
          "ratingType": "standard"
        },
        {
          "tournament": "www2025HobsonsBayWesternJuniors/data.json",
          "score": 3.5,
          "name": "2025 Hobsons Bay Western Juniors",
          "totalRounds": "5",
          "ratingType": "standard"
        },
        {
          "tournament": "www2025WesternJuniors/data.json",
          "score": 1,
          "name": "2025 Hobsons Bay Western Juniors",
          "totalRounds": "5",
          "ratingType": "standard"
        }
      ],
      "points": {
        "standard": 10.5,
        "rapid": 0,
        "blitz": 0
      }
    },
    {
      "name": "Husain,Lamiah",
      "id": "",
      "fideId": "3278905",
      "gender": "female",
      "href": "http://ratings.fide.com/card.phtml?event=3278905",
      "tournamentCount": 5,
      "tournaments": [
        {
          "tournament": "www2025HBCCHonourableBobJuniors/data.json",
          "score": 2,
          "name": "2025 HBCC Honourable Bob Juniors",
          "totalRounds": "5",
          "ratingType": "standard"
        },
        {
          "tournament": "www2025HobsonsBayPurdyCupJuniors/data.json",
          "score": 2,
          "name": "2025 Hobsons Bay Chess Club C.J.S Purdy Cup Juniors",
          "totalRounds": "5",
          "ratingType": "standard"
        },
        {
          "tournament": "www2025HobsonsBayWesternJuniors/data.json",
          "score": 1,
          "name": "2025 Hobsons Bay Western Juniors",
          "totalRounds": "5",
          "ratingType": "standard"
        },
        {
          "tournament": "www2025WesternJuniorRapidChampionship/data.json",
          "score": 3.5,
          "name": "2025 Hobsons Bay Western Juniors Rapid Championship",
          "totalRounds": "7",
          "ratingType": "rapid"
        },
        {
          "tournament": "www2025WesternJuniors/data.json",
          "score": 0,
          "name": "2025 Hobsons Bay Western Juniors",
          "totalRounds": "5",
          "ratingType": "standard"
        }
      ],
      "points": {
        "standard": 5,
        "rapid": 3.5,
        "blitz": 0
      }
    },
    {
      "name": "Itty Panicker,Prince",
      "id": "",
      "fideId": "3235726",
      "gender": "male",
      "href": "http://ratings.fide.com/card.phtml?event=3235726",
      "tournamentCount": 2,
      "tournaments": [
        {
          "tournament": "www2025HBCCHonourableBobJuniors/data.json",
          "score": 4,
          "name": "2025 HBCC Honourable Bob Juniors",
          "totalRounds": "5",
          "ratingType": "standard"
        },
        {
          "tournament": "www2025HobsonsBayPurdyCupJuniors/data.json",
          "score": 2,
          "name": "2025 Hobsons Bay Chess Club C.J.S Purdy Cup Juniors",
          "totalRounds": "5",
          "ratingType": "standard"
        }
      ],
      "points": {
        "standard": 6,
        "rapid": 0,
        "blitz": 0
      }
    },
    {
      "name": "Jagannathan,Shashvath",
      "id": "",
      "fideId": "",
      "gender": "male",
      "href": "",
      "tournamentCount": 5,
      "tournaments": [
        {
          "tournament": "www2025HBCCHonourableBobJuniors/data.json",
          "score": 2,
          "name": "2025 HBCC Honourable Bob Juniors",
          "totalRounds": "5",
          "ratingType": "standard"
        },
        {
          "tournament": "www2025HobsonsBayPurdyCupJuniors/data.json",
          "score": 2,
          "name": "2025 Hobsons Bay Chess Club C.J.S Purdy Cup Juniors",
          "totalRounds": "5",
          "ratingType": "standard"
        },
        {
          "tournament": "www2025HobsonsBayWesternJuniors/data.json",
          "score": 2.5,
          "name": "2025 Hobsons Bay Western Juniors",
          "totalRounds": "5",
          "ratingType": "standard"
        },
        {
          "tournament": "www2025WesternJuniorRapidChampionship/data.json",
          "score": 4,
          "name": "2025 Hobsons Bay Western Juniors Rapid Championship",
          "totalRounds": "7",
          "ratingType": "rapid"
        },
        {
          "tournament": "www2025WesternJuniors/data.json",
          "score": 1.5,
          "name": "2025 Hobsons Bay Western Juniors",
          "totalRounds": "5",
          "ratingType": "standard"
        }
      ],
      "points": {
        "standard": 8,
        "rapid": 4,
        "blitz": 0
      }
    },
    {
      "name": "Jyothi Nikhil,Neev",
      "id": "",
      "fideId": "3284670",
      "gender": "male",
      "href": "http://ratings.fide.com/card.phtml?event=3284670",
      "tournamentCount": 4,
      "tournaments": [
        {
          "tournament": "www2025HBCCHonourableBobJuniors/data.json",
          "score": 3,
          "name": "2025 HBCC Honourable Bob Juniors",
          "totalRounds": "5",
          "ratingType": "standard"
        },
        {
          "tournament": "www2025HobsonsBayWesternJuniors/data.json",
          "score": 3.5,
          "name": "2025 Hobsons Bay Western Juniors",
          "totalRounds": "5",
          "ratingType": "standard"
        },
        {
          "tournament": "www2025WesternJuniorRapidChampionship/data.json",
          "score": 4,
          "name": "2025 Hobsons Bay Western Juniors Rapid Championship",
          "totalRounds": "7",
          "ratingType": "rapid"
        },
        {
          "tournament": "www2025WesternJuniors/data.json",
          "score": 2,
          "name": "2025 Hobsons Bay Western Juniors",
          "totalRounds": "5",
          "ratingType": "standard"
        }
      ],
      "points": {
        "standard": 8.5,
        "rapid": 4,
        "blitz": 0
      }
    },
    {
      "name": "Kaki,Vihas",
      "id": "",
      "fideId": "",
      "gender": "male",
      "href": "",
      "tournamentCount": 2,
      "tournaments": [
        {
          "tournament": "www2025HobsonsBayWesternMini&RookiesJuniors/data.json",
          "score": 3,
          "name": "2025 Hobsons Bay Western Mini And Rookies Juniors",
          "totalRounds": "5",
          "ratingType": "standard"
        },
        {
          "tournament": "www2025HobsonsBayWesternMiniAndRookiesJuniors/data.json",
          "score": 1,
          "name": "2025 Hobsons Bay Western Mini And Rookies Juniors",
          "totalRounds": "5",
          "ratingType": "standard"
        }
      ],
      "points": {
        "standard": 4,
        "rapid": 0,
        "blitz": 0
      }
    },
    {
      "name": "Kantharaju,Aarna",
      "id": "",
      "fideId": "",
      "gender": "female",
      "href": "",
      "tournamentCount": 3,
      "tournaments": [
        {
          "tournament": "www2025HBCCHonourableBobJuniors/data.json",
          "score": 0,
          "name": "2025 HBCC Honourable Bob Juniors",
          "totalRounds": "5",
          "ratingType": "standard"
        },
        {
          "tournament": "www2025HobsonsBayWesternMini&RookiesJuniors/data.json",
          "score": 1,
          "name": "2025 Hobsons Bay Western Mini And Rookies Juniors",
          "totalRounds": "5",
          "ratingType": "standard"
        },
        {
          "tournament": "www2025HobsonsBayWesternMiniAndRookiesJuniors/data.json",
          "score": 0,
          "name": "2025 Hobsons Bay Western Mini And Rookies Juniors",
          "totalRounds": "5",
          "ratingType": "standard"
        }
      ],
      "points": {
        "standard": 1,
        "rapid": 0,
        "blitz": 0
      }
    },
    {
      "name": "Kantharaju,Aryan",
      "id": "",
      "fideId": "",
      "gender": "male",
      "href": "",
      "tournamentCount": 3,
      "tournaments": [
        {
          "tournament": "www2025HBCCHonourableBobJuniors/data.json",
          "score": 1,
          "name": "2025 HBCC Honourable Bob Juniors",
          "totalRounds": "5",
          "ratingType": "standard"
        },
        {
          "tournament": "www2025HobsonsBayWesternMini&RookiesJuniors/data.json",
          "score": 2,
          "name": "2025 Hobsons Bay Western Mini And Rookies Juniors",
          "totalRounds": "5",
          "ratingType": "standard"
        },
        {
          "tournament": "www2025HobsonsBayWesternMiniAndRookiesJuniors/data.json",
          "score": 1,
          "name": "2025 Hobsons Bay Western Mini And Rookies Juniors",
          "totalRounds": "5",
          "ratingType": "standard"
        }
      ],
      "points": {
        "standard": 4,
        "rapid": 0,
        "blitz": 0
      }
    },
    {
      "name": "Karthick,Deepshika",
      "id": "",
      "fideId": "3266583",
      "gender": "female",
      "href": "http://ratings.fide.com/card.phtml?event=3266583",
      "tournamentCount": 4,
      "tournaments": [
        {
          "tournament": "www2025HBCCHonourableBobJuniors/data.json",
          "score": 2.5,
          "name": "2025 HBCC Honourable Bob Juniors",
          "totalRounds": "5",
          "ratingType": "standard"
        },
        {
          "tournament": "www2025HobsonsBayPurdyCupJuniors/data.json",
          "score": 2.5,
          "name": "2025 Hobsons Bay Chess Club C.J.S Purdy Cup Juniors",
          "totalRounds": "5",
          "ratingType": "standard"
        },
        {
          "tournament": "www2025HobsonsBayWesternJuniors/data.json",
          "score": 3,
          "name": "2025 Hobsons Bay Western Juniors",
          "totalRounds": "5",
          "ratingType": "standard"
        },
        {
          "tournament": "www2025WesternJuniors/data.json",
          "score": 1,
          "name": "2025 Hobsons Bay Western Juniors",
          "totalRounds": "5",
          "ratingType": "standard"
        }
      ],
      "points": {
        "standard": 9,
        "rapid": 0,
        "blitz": 0
      }
    },
    {
      "name": "Kelly,Jackson",
      "id": "",
      "fideId": "",
      "gender": "male",
      "href": "",
      "tournamentCount": 4,
      "tournaments": [
        {
          "tournament": "www2025HobsonsBayPurdyCupJuniors/data.json",
          "score": 1,
          "name": "2025 Hobsons Bay Chess Club C.J.S Purdy Cup Juniors",
          "totalRounds": "5",
          "ratingType": "standard"
        },
        {
          "tournament": "www2025HobsonsBayWesternMini&RookiesJuniors/data.json",
          "score": 1.5,
          "name": "2025 Hobsons Bay Western Mini And Rookies Juniors",
          "totalRounds": "5",
          "ratingType": "standard"
        },
        {
          "tournament": "www2025HobsonsBayWesternMiniAndRookiesJuniors/data.json",
          "score": 0.5,
          "name": "2025 Hobsons Bay Western Mini And Rookies Juniors",
          "totalRounds": "5",
          "ratingType": "standard"
        },
        {
          "tournament": "www2025WesternJuniorRapidChampionship/data.json",
          "score": 1,
          "name": "2025 Hobsons Bay Western Juniors Rapid Championship",
          "totalRounds": "7",
          "ratingType": "rapid"
        }
      ],
      "points": {
        "standard": 3,
        "rapid": 1,
        "blitz": 0
      }
    },
    {
      "name": "Kirk,Ian",
      "id": "",
      "fideId": "3247953",
      "gender": "male",
      "href": "http://ratings.fide.com/card.phtml?event=3247953",
      "tournamentCount": 3,
      "tournaments": [
        {
          "tournament": "www2025HobsonsBayPurdyCupJuniors/data.json",
          "score": 4,
          "name": "2025 Hobsons Bay Chess Club C.J.S Purdy Cup Juniors",
          "totalRounds": "5",
          "ratingType": "standard"
        },
        {
          "tournament": "www2025HobsonsBayWesternJuniors/data.json",
          "score": 3,
          "name": "2025 Hobsons Bay Western Juniors",
          "totalRounds": "5",
          "ratingType": "standard"
        },
        {
          "tournament": "www2025WesternJuniors/data.json",
          "score": 1,
          "name": "2025 Hobsons Bay Western Juniors",
          "totalRounds": "5",
          "ratingType": "standard"
        }
      ],
      "points": {
        "standard": 8,
        "rapid": 0,
        "blitz": 0
      }
    },
    {
      "name": "Kwek,Alexander",
      "id": "",
      "fideId": "",
      "gender": "male",
      "href": "",
      "tournamentCount": 2,
      "tournaments": [
        {
          "tournament": "www2025HobsonsBayWesternMini&RookiesJuniors/data.json",
          "score": 1.5,
          "name": "2025 Hobsons Bay Western Mini And Rookies Juniors",
          "totalRounds": "5",
          "ratingType": "standard"
        },
        {
          "tournament": "www2025HobsonsBayWesternMiniAndRookiesJuniors/data.json",
          "score": 1.5,
          "name": "2025 Hobsons Bay Western Mini And Rookies Juniors",
          "totalRounds": "5",
          "ratingType": "standard"
        }
      ],
      "points": {
        "standard": 3,
        "rapid": 0,
        "blitz": 0
      }
    },
    {
      "name": "Majety,Rohan",
      "id": "",
      "fideId": "3260062",
      "gender": "male",
      "href": "http://ratings.fide.com/card.phtml?event=3260062",
      "tournamentCount": 3,
      "tournaments": [
        {
          "tournament": "www2025HBCCHonourableBobJuniors/data.json",
          "score": 3,
          "name": "2025 HBCC Honourable Bob Juniors",
          "totalRounds": "5",
          "ratingType": "standard"
        },
        {
          "tournament": "www2025HobsonsBayPurdyCupJuniors/data.json",
          "score": 3.5,
          "name": "2025 Hobsons Bay Chess Club C.J.S Purdy Cup Juniors",
          "totalRounds": "5",
          "ratingType": "standard"
        },
        {
          "tournament": "www2025WesternJuniorRapidChampionship/data.json",
          "score": 3.5,
          "name": "2025 Hobsons Bay Western Juniors Rapid Championship",
          "totalRounds": "7",
          "ratingType": "rapid"
        }
      ],
      "points": {
        "standard": 6.5,
        "rapid": 3.5,
        "blitz": 0
      }
    },
    {
      "name": "Manoj,Dev",
      "id": "",
      "fideId": "3283470",
      "gender": "male",
      "href": "http://ratings.fide.com/card.phtml?event=3283470",
      "tournamentCount": 2,
      "tournaments": [
        {
          "tournament": "www2025HBCCHonourableBobJuniors/data.json",
          "score": 2,
          "name": "2025 HBCC Honourable Bob Juniors",
          "totalRounds": "5",
          "ratingType": "standard"
        },
        {
          "tournament": "www2025WesternJuniorRapidChampionship/data.json",
          "score": 2,
          "name": "2025 Hobsons Bay Western Juniors Rapid Championship",
          "totalRounds": "7",
          "ratingType": "rapid"
        }
      ],
      "points": {
        "standard": 2,
        "rapid": 2,
        "blitz": 0
      }
    },
    {
      "name": "Matijas,Dejan",
      "id": "",
      "fideId": "3242838",
      "gender": "male",
      "href": "http://ratings.fide.com/card.phtml?event=3242838",
      "tournamentCount": 2,
      "tournaments": [
        {
          "tournament": "www2025HBCCHonourableBobJuniors/data.json",
          "score": 3,
          "name": "2025 HBCC Honourable Bob Juniors",
          "totalRounds": "5",
          "ratingType": "standard"
        },
        {
          "tournament": "www2025HobsonsBayPurdyCupJuniors/data.json",
          "score": 3.5,
          "name": "2025 Hobsons Bay Chess Club C.J.S Purdy Cup Juniors",
          "totalRounds": "5",
          "ratingType": "standard"
        }
      ],
      "points": {
        "standard": 6.5,
        "rapid": 0,
        "blitz": 0
      }
    },
    {
      "name": "Morris,Elijah",
      "id": "",
      "fideId": "",
      "gender": "male",
      "href": "",
      "tournamentCount": 5,
      "tournaments": [
        {
          "tournament": "www2025HBCCHonourableBobJuniors/data.json",
          "score": 2,
          "name": "2025 HBCC Honourable Bob Juniors",
          "totalRounds": "5",
          "ratingType": "standard"
        },
        {
          "tournament": "www2025HobsonsBayPurdyCupJuniors/data.json",
          "score": 2,
          "name": "2025 Hobsons Bay Chess Club C.J.S Purdy Cup Juniors",
          "totalRounds": "5",
          "ratingType": "standard"
        },
        {
          "tournament": "www2025HobsonsBayWesternJuniors/data.json",
          "score": 1.5,
          "name": "2025 Hobsons Bay Western Juniors",
          "totalRounds": "5",
          "ratingType": "standard"
        },
        {
          "tournament": "www2025WesternJuniorRapidChampionship/data.json",
          "score": 3.5,
          "name": "2025 Hobsons Bay Western Juniors Rapid Championship",
          "totalRounds": "7",
          "ratingType": "rapid"
        },
        {
          "tournament": "www2025WesternJuniors/data.json",
          "score": 1,
          "name": "2025 Hobsons Bay Western Juniors",
          "totalRounds": "5",
          "ratingType": "standard"
        }
      ],
      "points": {
        "standard": 6.5,
        "rapid": 3.5,
        "blitz": 0
      }
    },
    {
      "name": "Mukunth,Ganesh Kumar",
      "id": "",
      "fideId": "",
      "gender": "male",
      "href": "",
      "tournamentCount": 2,
      "tournaments": [
        {
          "tournament": "www2025HobsonsBayWesternMini&RookiesJuniors/data.json",
          "score": 3,
          "name": "2025 Hobsons Bay Western Mini And Rookies Juniors",
          "totalRounds": "5",
          "ratingType": "standard"
        },
        {
          "tournament": "www2025HobsonsBayWesternMiniAndRookiesJuniors/data.json",
          "score": 1,
          "name": "2025 Hobsons Bay Western Mini And Rookies Juniors",
          "totalRounds": "5",
          "ratingType": "standard"
        }
      ],
      "points": {
        "standard": 4,
        "rapid": 0,
        "blitz": 0
      }
    },
    {
      "name": "Naidu,Aarush",
      "id": "",
      "fideId": "",
      "gender": "male",
      "href": "",
      "tournamentCount": 2,
      "tournaments": [
        {
          "tournament": "www2025HBCCHonourableBobJuniors/data.json",
          "score": 2,
          "name": "2025 HBCC Honourable Bob Juniors",
          "totalRounds": "5",
          "ratingType": "standard"
        },
        {
          "tournament": "www2025WesternJuniorRapidChampionship/data.json",
          "score": 2,
          "name": "2025 Hobsons Bay Western Juniors Rapid Championship",
          "totalRounds": "7",
          "ratingType": "rapid"
        }
      ],
      "points": {
        "standard": 2,
        "rapid": 2,
        "blitz": 0
      }
    },
    {
      "name": "Nema,Nivaan",
      "id": "",
      "fideId": "",
      "gender": "male",
      "href": "",
      "tournamentCount": 4,
      "tournaments": [
        {
          "tournament": "www2025HobsonsBayPurdyCupJuniors/data.json",
          "score": 2,
          "name": "2025 Hobsons Bay Chess Club C.J.S Purdy Cup Juniors",
          "totalRounds": "5",
          "ratingType": "standard"
        },
        {
          "tournament": "www2025HobsonsBayWesternMini&RookiesJuniors/data.json",
          "score": 4,
          "name": "2025 Hobsons Bay Western Mini And Rookies Juniors",
          "totalRounds": "5",
          "ratingType": "standard"
        },
        {
          "tournament": "www2025HobsonsBayWesternMiniAndRookiesJuniors/data.json",
          "score": 1,
          "name": "2025 Hobsons Bay Western Mini And Rookies Juniors",
          "totalRounds": "5",
          "ratingType": "standard"
        },
        {
          "tournament": "www2025WesternJuniorRapidChampionship/data.json",
          "score": 3.5,
          "name": "2025 Hobsons Bay Western Juniors Rapid Championship",
          "totalRounds": "7",
          "ratingType": "rapid"
        }
      ],
      "points": {
        "standard": 7,
        "rapid": 3.5,
        "blitz": 0
      }
    },
    {
      "name": "Nguyen,Anh Kiet",
      "id": "",
      "fideId": "3267849",
      "gender": "male",
      "href": "http://ratings.fide.com/card.phtml?event=3267849",
      "tournamentCount": 3,
      "tournaments": [
        {
          "tournament": "www2025HBCCHonourableBobJuniors/data.json",
          "score": 4.5,
          "name": "2025 HBCC Honourable Bob Juniors",
          "totalRounds": "5",
          "ratingType": "standard"
        },
        {
          "tournament": "www2025HobsonsBayPurdyCupJuniors/data.json",
          "score": 5,
          "name": "2025 Hobsons Bay Chess Club C.J.S Purdy Cup Juniors",
          "totalRounds": "5",
          "ratingType": "standard"
        },
        {
          "tournament": "www2025WesternJuniorRapidChampionship/data.json",
          "score": 5,
          "name": "2025 Hobsons Bay Western Juniors Rapid Championship",
          "totalRounds": "7",
          "ratingType": "rapid"
        }
      ],
      "points": {
        "standard": 9.5,
        "rapid": 5,
        "blitz": 0
      }
    },
    {
      "name": "Nguyen,Tuan Kiet",
      "id": "",
      "fideId": "3270335",
      "gender": "male",
      "href": "http://ratings.fide.com/card.phtml?event=3270335",
      "tournamentCount": 5,
      "tournaments": [
        {
          "tournament": "www2025HBCCHonourableBobJuniors/data.json",
          "score": 2.5,
          "name": "2025 HBCC Honourable Bob Juniors",
          "totalRounds": "5",
          "ratingType": "standard"
        },
        {
          "tournament": "www2025HobsonsBayPurdyCupJuniors/data.json",
          "score": 3,
          "name": "2025 Hobsons Bay Chess Club C.J.S Purdy Cup Juniors",
          "totalRounds": "5",
          "ratingType": "standard"
        },
        {
          "tournament": "www2025HobsonsBayWesternJuniors/data.json",
          "score": 2,
          "name": "2025 Hobsons Bay Western Juniors",
          "totalRounds": "5",
          "ratingType": "standard"
        },
        {
          "tournament": "www2025WesternJuniorRapidChampionship/data.json",
          "score": 4,
          "name": "2025 Hobsons Bay Western Juniors Rapid Championship",
          "totalRounds": "7",
          "ratingType": "rapid"
        },
        {
          "tournament": "www2025WesternJuniors/data.json",
          "score": 1,
          "name": "2025 Hobsons Bay Western Juniors",
          "totalRounds": "5",
          "ratingType": "standard"
        }
      ],
      "points": {
        "standard": 8.5,
        "rapid": 4,
        "blitz": 0
      }
    },
    {
      "name": "Prince,Aliza",
      "id": "",
      "fideId": "3283941",
      "gender": "female",
      "href": "http://ratings.fide.com/card.phtml?event=3283941",
      "tournamentCount": 2,
      "tournaments": [
        {
          "tournament": "www2025HBCCHonourableBobJuniors/data.json",
          "score": 2,
          "name": "2025 HBCC Honourable Bob Juniors",
          "totalRounds": "5",
          "ratingType": "standard"
        },
        {
          "tournament": "www2025HobsonsBayPurdyCupJuniors/data.json",
          "score": 1,
          "name": "2025 Hobsons Bay Chess Club C.J.S Purdy Cup Juniors",
          "totalRounds": "5",
          "ratingType": "standard"
        }
      ],
      "points": {
        "standard": 3,
        "rapid": 0,
        "blitz": 0
      }
    },
    {
      "name": "Ramanathan,Ashwin",
      "id": "",
      "fideId": "3275221",
      "gender": "male",
      "href": "http://ratings.fide.com/card.phtml?event=3275221",
      "tournamentCount": 3,
      "tournaments": [
        {
          "tournament": "www2025HBCCHonourableBobJuniors/data.json",
          "score": 3.5,
          "name": "2025 HBCC Honourable Bob Juniors",
          "totalRounds": "5",
          "ratingType": "standard"
        },
        {
          "tournament": "www2025HobsonsBayPurdyCupJuniors/data.json",
          "score": 4,
          "name": "2025 Hobsons Bay Chess Club C.J.S Purdy Cup Juniors",
          "totalRounds": "5",
          "ratingType": "standard"
        },
        {
          "tournament": "www2025WesternJuniorRapidChampionship/data.json",
          "score": 5,
          "name": "2025 Hobsons Bay Western Juniors Rapid Championship",
          "totalRounds": "7",
          "ratingType": "rapid"
        }
      ],
      "points": {
        "standard": 7.5,
        "rapid": 5,
        "blitz": 0
      }
    },
    {
      "name": "Ramprasad,Nachiket",
      "id": "",
      "fideId": "",
      "gender": "male",
      "href": "",
      "tournamentCount": 2,
      "tournaments": [
        {
          "tournament": "www2025HBCCHonourableBobJuniors/data.json",
          "score": 4,
          "name": "2025 HBCC Honourable Bob Juniors",
          "totalRounds": "5",
          "ratingType": "standard"
        },
        {
          "tournament": "www2025HobsonsBayPurdyCupJuniors/data.json",
          "score": 3.5,
          "name": "2025 Hobsons Bay Chess Club C.J.S Purdy Cup Juniors",
          "totalRounds": "5",
          "ratingType": "standard"
        }
      ],
      "points": {
        "standard": 7.5,
        "rapid": 0,
        "blitz": 0
      }
    },
    {
      "name": "Rawat,Pratyax Singh",
      "id": "",
      "fideId": "3287440",
      "gender": "male",
      "href": "http://ratings.fide.com/card.phtml?event=3287440",
      "tournamentCount": 3,
      "tournaments": [
        {
          "tournament": "www2025HobsonsBayPurdyCupJuniors/data.json",
          "score": 1,
          "name": "2025 Hobsons Bay Chess Club C.J.S Purdy Cup Juniors",
          "totalRounds": "5",
          "ratingType": "standard"
        },
        {
          "tournament": "www2025HobsonsBayWesternMini&RookiesJuniors/data.json",
          "score": 2,
          "name": "2025 Hobsons Bay Western Mini And Rookies Juniors",
          "totalRounds": "5",
          "ratingType": "standard"
        },
        {
          "tournament": "www2025HobsonsBayWesternMiniAndRookiesJuniors/data.json",
          "score": 1,
          "name": "2025 Hobsons Bay Western Mini And Rookies Juniors",
          "totalRounds": "5",
          "ratingType": "standard"
        }
      ],
      "points": {
        "standard": 4,
        "rapid": 0,
        "blitz": 0
      }
    },
    {
      "name": "Ruaya,Rohan",
      "id": "",
      "fideId": "3281345",
      "gender": "male",
      "href": "http://ratings.fide.com/card.phtml?event=3281345",
      "tournamentCount": 5,
      "tournaments": [
        {
          "tournament": "www2025HBCCHonourableBobJuniors/data.json",
          "score": 2,
          "name": "2025 HBCC Honourable Bob Juniors",
          "totalRounds": "5",
          "ratingType": "standard"
        },
        {
          "tournament": "www2025HobsonsBayPurdyCupJuniors/data.json",
          "score": 3.5,
          "name": "2025 Hobsons Bay Chess Club C.J.S Purdy Cup Juniors",
          "totalRounds": "5",
          "ratingType": "standard"
        },
        {
          "tournament": "www2025HobsonsBayWesternJuniors/data.json",
          "score": 2,
          "name": "2025 Hobsons Bay Western Juniors",
          "totalRounds": "5",
          "ratingType": "standard"
        },
        {
          "tournament": "www2025WesternJuniorRapidChampionship/data.json",
          "score": 4,
          "name": "2025 Hobsons Bay Western Juniors Rapid Championship",
          "totalRounds": "7",
          "ratingType": "rapid"
        },
        {
          "tournament": "www2025WesternJuniors/data.json",
          "score": 1,
          "name": "2025 Hobsons Bay Western Juniors",
          "totalRounds": "5",
          "ratingType": "standard"
        }
      ],
      "points": {
        "standard": 8.5,
        "rapid": 4,
        "blitz": 0
      }
    },
    {
      "name": "Saha,Avinandan (Arjun)",
      "id": "",
      "fideId": "3264173",
      "gender": "male",
      "href": "http://ratings.fide.com/card.phtml?event=3264173",
      "tournamentCount": 5,
      "tournaments": [
        {
          "tournament": "www2025HBCCHonourableBobJuniors/data.json",
          "score": 3,
          "name": "2025 HBCC Honourable Bob Juniors",
          "totalRounds": "5",
          "ratingType": "standard"
        },
        {
          "tournament": "www2025HobsonsBayPurdyCupJuniors/data.json",
          "score": 3,
          "name": "2025 Hobsons Bay Chess Club C.J.S Purdy Cup Juniors",
          "totalRounds": "5",
          "ratingType": "standard"
        },
        {
          "tournament": "www2025HobsonsBayWesternJuniors/data.json",
          "score": 0.5,
          "name": "2025 Hobsons Bay Western Juniors",
          "totalRounds": "5",
          "ratingType": "standard"
        },
        {
          "tournament": "www2025WesternJuniorRapidChampionship/data.json",
          "score": 5,
          "name": "2025 Hobsons Bay Western Juniors Rapid Championship",
          "totalRounds": "7",
          "ratingType": "rapid"
        },
        {
          "tournament": "www2025WesternJuniors/data.json",
          "score": 0.5,
          "name": "2025 Hobsons Bay Western Juniors",
          "totalRounds": "5",
          "ratingType": "standard"
        }
      ],
      "points": {
        "standard": 7,
        "rapid": 5,
        "blitz": 0
      }
    },
    {
      "name": "Settu,Karthick",
      "id": "",
      "fideId": "3267865",
      "gender": "male",
      "href": "http://ratings.fide.com/card.phtml?event=3267865",
      "tournamentCount": 2,
      "tournaments": [
        {
          "tournament": "www2025HBCCHonourableBobJuniors/data.json",
          "score": 2.5,
          "name": "2025 HBCC Honourable Bob Juniors",
          "totalRounds": "5",
          "ratingType": "standard"
        },
        {
          "tournament": "www2025HobsonsBayPurdyCupJuniors/data.json",
          "score": 2.5,
          "name": "2025 Hobsons Bay Chess Club C.J.S Purdy Cup Juniors",
          "totalRounds": "5",
          "ratingType": "standard"
        }
      ],
      "points": {
        "standard": 5,
        "rapid": 0,
        "blitz": 0
      }
    },
    {
      "name": "Shaiek,Nihal",
      "id": "",
      "fideId": "",
      "gender": "male",
      "href": "",
      "tournamentCount": 5,
      "tournaments": [
        {
          "tournament": "www2025HBCCHonourableBobJuniors/data.json",
          "score": 3,
          "name": "2025 HBCC Honourable Bob Juniors",
          "totalRounds": "5",
          "ratingType": "standard"
        },
        {
          "tournament": "www2025HobsonsBayPurdyCupJuniors/data.json",
          "score": 2,
          "name": "2025 Hobsons Bay Chess Club C.J.S Purdy Cup Juniors",
          "totalRounds": "5",
          "ratingType": "standard"
        },
        {
          "tournament": "www2025HobsonsBayWesternJuniors/data.json",
          "score": 1.5,
          "name": "2025 Hobsons Bay Western Juniors",
          "totalRounds": "5",
          "ratingType": "standard"
        },
        {
          "tournament": "www2025WesternJuniorRapidChampionship/data.json",
          "score": 3.5,
          "name": "2025 Hobsons Bay Western Juniors Rapid Championship",
          "totalRounds": "7",
          "ratingType": "rapid"
        },
        {
          "tournament": "www2025WesternJuniors/data.json",
          "score": 0,
          "name": "2025 Hobsons Bay Western Juniors",
          "totalRounds": "5",
          "ratingType": "standard"
        }
      ],
      "points": {
        "standard": 6.5,
        "rapid": 3.5,
        "blitz": 0
      }
    },
    {
      "name": "Shinde,Yug",
      "id": "",
      "fideId": "537082183",
      "gender": "male",
      "href": "http://ratings.fide.com/card.phtml?event=537082183",
      "tournamentCount": 4,
      "tournaments": [
        {
          "tournament": "www2025HBCCHonourableBobJuniors/data.json",
          "score": 2.5,
          "name": "2025 HBCC Honourable Bob Juniors",
          "totalRounds": "5",
          "ratingType": "standard"
        },
        {
          "tournament": "www2025HobsonsBayPurdyCupJuniors/data.json",
          "score": 2,
          "name": "2025 Hobsons Bay Chess Club C.J.S Purdy Cup Juniors",
          "totalRounds": "5",
          "ratingType": "standard"
        },
        {
          "tournament": "www2025HobsonsBayWesternJuniors/data.json",
          "score": 2,
          "name": "2025 Hobsons Bay Western Juniors",
          "totalRounds": "5",
          "ratingType": "standard"
        },
        {
          "tournament": "www2025WesternJuniors/data.json",
          "score": 1,
          "name": "2025 Hobsons Bay Western Juniors",
          "totalRounds": "5",
          "ratingType": "standard"
        }
      ],
      "points": {
        "standard": 7.5,
        "rapid": 0,
        "blitz": 0
      }
    },
    {
      "name": "Spriggs,Harvey",
      "id": "",
      "fideId": "",
      "gender": "male",
      "href": "",
      "tournamentCount": 2,
      "tournaments": [
        {
          "tournament": "www2025HobsonsBayPurdyCupJuniors/data.json",
          "score": 2,
          "name": "2025 Hobsons Bay Chess Club C.J.S Purdy Cup Juniors",
          "totalRounds": "5",
          "ratingType": "standard"
        },
        {
          "tournament": "www2025WesternJuniorRapidChampionship/data.json",
          "score": 3,
          "name": "2025 Hobsons Bay Western Juniors Rapid Championship",
          "totalRounds": "7",
          "ratingType": "rapid"
        }
      ],
      "points": {
        "standard": 2,
        "rapid": 3,
        "blitz": 0
      }
    },
    {
      "name": "Stefan Tham,Keanu",
      "id": "",
      "fideId": "3286401",
      "gender": "male",
      "href": "http://ratings.fide.com/card.phtml?event=3286401",
      "tournamentCount": 2,
      "tournaments": [
        {
          "tournament": "www2025HobsonsBayWesternMini&RookiesJuniors/data.json",
          "score": 4,
          "name": "2025 Hobsons Bay Western Mini And Rookies Juniors",
          "totalRounds": "5",
          "ratingType": "standard"
        },
        {
          "tournament": "www2025HobsonsBayWesternMiniAndRookiesJuniors/data.json",
          "score": 1.5,
          "name": "2025 Hobsons Bay Western Mini And Rookies Juniors",
          "totalRounds": "5",
          "ratingType": "standard"
        }
      ],
      "points": {
        "standard": 5.5,
        "rapid": 0,
        "blitz": 0
      }
    },
    {
      "name": "Veginati,Cherish",
      "id": "",
      "fideId": "3275248",
      "gender": "male",
      "href": "http://ratings.fide.com/card.phtml?event=3275248",
      "tournamentCount": 3,
      "tournaments": [
        {
          "tournament": "www2025HobsonsBayPurdyCupJuniors/data.json",
          "score": 2,
          "name": "2025 Hobsons Bay Chess Club C.J.S Purdy Cup Juniors",
          "totalRounds": "5",
          "ratingType": "standard"
        },
        {
          "tournament": "www2025HobsonsBayWesternJuniors/data.json",
          "score": 3.5,
          "name": "2025 Hobsons Bay Western Juniors",
          "totalRounds": "5",
          "ratingType": "standard"
        },
        {
          "tournament": "www2025WesternJuniors/data.json",
          "score": 1.5,
          "name": "2025 Hobsons Bay Western Juniors",
          "totalRounds": "5",
          "ratingType": "standard"
        }
      ],
      "points": {
        "standard": 7,
        "rapid": 0,
        "blitz": 0
      }
    },
    {
      "name": "Vemula,Thamoghna",
      "id": "",
      "fideId": "",
      "gender": "male",
      "href": "",
      "tournamentCount": 3,
      "tournaments": [
        {
          "tournament": "www2025HobsonsBayWesternMini&RookiesJuniors/data.json",
          "score": 4,
          "name": "2025 Hobsons Bay Western Mini And Rookies Juniors",
          "totalRounds": "5",
          "ratingType": "standard"
        },
        {
          "tournament": "www2025HobsonsBayWesternMiniAndRookiesJuniors/data.json",
          "score": 2,
          "name": "2025 Hobsons Bay Western Mini And Rookies Juniors",
          "totalRounds": "5",
          "ratingType": "standard"
        },
        {
          "tournament": "www2025WesternJuniorRapidChampionship/data.json",
          "score": 3,
          "name": "2025 Hobsons Bay Western Juniors Rapid Championship",
          "totalRounds": "7",
          "ratingType": "rapid"
        }
      ],
      "points": {
        "standard": 6,
        "rapid": 3,
        "blitz": 0
      }
    },
    {
      "name": "Venkat,Nyra",
      "id": "",
      "fideId": "",
      "gender": "female",
      "href": "",
      "tournamentCount": 5,
      "tournaments": [
        {
          "tournament": "www2025HBCCHonourableBobJuniors/data.json",
          "score": 2,
          "name": "2025 HBCC Honourable Bob Juniors",
          "totalRounds": "5",
          "ratingType": "standard"
        },
        {
          "tournament": "www2025HobsonsBayPurdyCupJuniors/data.json",
          "score": 1,
          "name": "2025 Hobsons Bay Chess Club C.J.S Purdy Cup Juniors",
          "totalRounds": "5",
          "ratingType": "standard"
        },
        {
          "tournament": "www2025HobsonsBayWesternMini&RookiesJuniors/data.json",
          "score": 1.5,
          "name": "2025 Hobsons Bay Western Mini And Rookies Juniors",
          "totalRounds": "5",
          "ratingType": "standard"
        },
        {
          "tournament": "www2025HobsonsBayWesternMiniAndRookiesJuniors/data.json",
          "score": 0,
          "name": "2025 Hobsons Bay Western Mini And Rookies Juniors",
          "totalRounds": "5",
          "ratingType": "standard"
        },
        {
          "tournament": "www2025WesternJuniorRapidChampionship/data.json",
          "score": 3,
          "name": "2025 Hobsons Bay Western Juniors Rapid Championship",
          "totalRounds": "7",
          "ratingType": "rapid"
        }
      ],
      "points": {
        "standard": 4.5,
        "rapid": 3,
        "blitz": 0
      }
    },
    {
      "name": "Wei,Andrew",
      "id": "",
      "fideId": "3265277",
      "gender": "male",
      "href": "http://ratings.fide.com/card.phtml?event=3265277",
      "tournamentCount": 4,
      "tournaments": [
        {
          "tournament": "www2025HBCCHonourableBobJuniors/data.json",
          "score": 3,
          "name": "2025 HBCC Honourable Bob Juniors",
          "totalRounds": "5",
          "ratingType": "standard"
        },
        {
          "tournament": "www2025HobsonsBayPurdyCupJuniors/data.json",
          "score": 1.5,
          "name": "2025 Hobsons Bay Chess Club C.J.S Purdy Cup Juniors",
          "totalRounds": "5",
          "ratingType": "standard"
        },
        {
          "tournament": "www2025HobsonsBayWesternJuniors/data.json",
          "score": 2.5,
          "name": "2025 Hobsons Bay Western Juniors",
          "totalRounds": "5",
          "ratingType": "standard"
        },
        {
          "tournament": "www2025WesternJuniors/data.json",
          "score": 1,
          "name": "2025 Hobsons Bay Western Juniors",
          "totalRounds": "5",
          "ratingType": "standard"
        }
      ],
      "points": {
        "standard": 8,
        "rapid": 0,
        "blitz": 0
      }
    },
    {
      "name": "Yang,Yifan",
      "id": "",
      "fideId": "3275272",
      "gender": "male",
      "href": "http://ratings.fide.com/card.phtml?event=3275272",
      "tournamentCount": 2,
      "tournaments": [
        {
          "tournament": "www2025HBCCHonourableBobJuniors/data.json",
          "score": 3.5,
          "name": "2025 HBCC Honourable Bob Juniors",
          "totalRounds": "5",
          "ratingType": "standard"
        },
        {
          "tournament": "www2025HobsonsBayPurdyCupJuniors/data.json",
          "score": 3,
          "name": "2025 Hobsons Bay Chess Club C.J.S Purdy Cup Juniors",
          "totalRounds": "5",
          "ratingType": "standard"
        }
      ],
      "points": {
        "standard": 6.5,
        "rapid": 0,
        "blitz": 0
      }
    },
    {
      "name": "Yendru,Srikrishna",
      "id": "",
      "fideId": "3262952",
      "gender": "male",
      "href": "http://ratings.fide.com/card.phtml?event=3262952",
      "tournamentCount": 3,
      "tournaments": [
        {
          "tournament": "www2025HobsonsBayPurdyCupJuniors/data.json",
          "score": 3.5,
          "name": "2025 Hobsons Bay Chess Club C.J.S Purdy Cup Juniors",
          "totalRounds": "5",
          "ratingType": "standard"
        },
        {
          "tournament": "www2025HobsonsBayWesternJuniors/data.json",
          "score": 2,
          "name": "2025 Hobsons Bay Western Juniors",
          "totalRounds": "5",
          "ratingType": "standard"
        },
        {
          "tournament": "www2025WesternJuniors/data.json",
          "score": 1,
          "name": "2025 Hobsons Bay Western Juniors",
          "totalRounds": "5",
          "ratingType": "standard"
        }
      ],
      "points": {
        "standard": 6.5,
        "rapid": 0,
        "blitz": 0
      }
    },
    {
      "name": "Yendru,Sriram",
      "id": "",
      "fideId": "3267881",
      "gender": "male",
      "href": "http://ratings.fide.com/card.phtml?event=3267881",
      "tournamentCount": 2,
      "tournaments": [
        {
          "tournament": "www2025HobsonsBayWesternMini&RookiesJuniors/data.json",
          "score": 4,
          "name": "2025 Hobsons Bay Western Mini And Rookies Juniors",
          "totalRounds": "5",
          "ratingType": "standard"
        },
        {
          "tournament": "www2025HobsonsBayWesternMiniAndRookiesJuniors/data.json",
          "score": 1,
          "name": "2025 Hobsons Bay Western Mini And Rookies Juniors",
          "totalRounds": "5",
          "ratingType": "standard"
        }
      ],
      "points": {
        "standard": 5,
        "rapid": 0,
        "blitz": 0
      }
    }
  ]
}